strangeworks_remote_job/__init__.py
strangeworks_remote_job/admin.py
strangeworks_remote_job/app/__init__.py
strangeworks_remote_job/app/main.py
strangeworks_remote_job/app/middleware.py
strangeworks_remote_job/app/routers/__init__.py
strangeworks_remote_job/app/routers/admin.py
strangeworks_remote_job/app/routers/jobs.py
strangeworks_remote_job/app/routers/types/job.py
strangeworks_remote_job/app.py
strangeworks_remote_job/artifact.py
strangeworks_remote_job/basic.py
strangeworks_remote_job/ex.py
strangeworks_remote_job/modal.py
strangeworks_remote_job/remote.py
remote_job_app-0.1.15.dist-info/METADATA
remote_job_app-0.1.15.dist-info/WHEEL
remote_job_app-0.1.15.dist-info/RECORD
